agi_agents/__init__.py
agi_agents/agi_agent.py
agi_agents-0.2.1.dist-info/licenses/LICENSE
agi_agents-0.2.1.dist-info/METADATA
agi_agents-0.2.1.dist-info/WHEEL
agi_agents-0.2.1.dist-info/top_level.txt
agi_agents-0.2.1.dist-info/RECORD
