Metadata-Version: 2.4
Name: agi-agents
Version: 0.2.1
Summary: A streamlined interface for LangChain based AI agent creation with multi-modal support
Home-page: https://github.com/YvonneYS-DU/agi_agents
Author: YvonneYS-Du
Author-email: YvonneYS-Du <yvdu.ai2077@gmail.com>
License: MIT
Project-URL: Homepage, https://github.com/YvonneYS-DU/agi_agents
Project-URL: Repository, https://github.com/YvonneYS-DU/agi_agents
Project-URL: Bug Reports, https://github.com/YvonneYS-DU/agi_agents/issues
Keywords: langchain,ai,llm,multimodal,agents,wrapper
Classifier: Development Status :: 4 - Beta
Classifier: Intended Audience :: Developers
Classifier: License :: OSI Approved :: MIT License
Classifier: Operating System :: OS Independent
Classifier: Programming Language :: Python :: 3
Classifier: Programming Language :: Python :: 3.8
Classifier: Programming Language :: Python :: 3.9
Classifier: Programming Language :: Python :: 3.10
Classifier: Programming Language :: Python :: 3.11
Classifier: Programming Language :: Python :: 3.12
Classifier: Topic :: Software Development :: Libraries :: Python Modules
Classifier: Topic :: Scientific/Engineering :: Artificial Intelligence
Requires-Python: >=3.8
License-File: LICENSE
Requires-Dist: langchain<0.4.0,>=0.3.0
Requires-Dist: langchain-core<0.4.0,>=0.3.5
Requires-Dist: langchain-openai>=0.1.0
Requires-Dist: langchain-anthropic>=0.1.0
Requires-Dist: langchain-text-splitters>=0.3.0
Requires-Dist: openai<2.0.0,>=1.76.0
Requires-Dist: anthropic<1.0.0,>=0.40.0
Requires-Dist: httpx<0.28.0,>=0.27.2
Requires-Dist: aiohttp>=3.8.0
Requires-Dist: aiofiles>=23.0.0
Requires-Dist: PyMuPDF>=1.20.0
Requires-Dist: python-docx>=1.0.0
Requires-Dist: unstructured>=0.15.0
Requires-Dist: openpyxl>=3.1.0
Requires-Dist: Pillow>=9.0.0
Requires-Dist: pillow-heif>=0.8.0
Requires-Dist: pandas>=1.5.0
Requires-Dist: regex>=2020.1.1
Requires-Dist: azure-storage-blob>=12.0.0
Requires-Dist: python-dotenv>=1.0.0
Requires-Dist: urllib3>=2.0.0
Provides-Extra: dev
Requires-Dist: pytest>=6.0.0; extra == "dev"
Requires-Dist: black>=22.0.0; extra == "dev"
Requires-Dist: flake8>=4.0.0; extra == "dev"
Requires-Dist: mypy>=0.900; extra == "dev"
Provides-Extra: docs
Requires-Dist: sphinx>=4.0.0; extra == "docs"
Requires-Dist: sphinx-rtd-theme>=1.0.0; extra == "docs"
Dynamic: author
Dynamic: home-page
Dynamic: license-file
Dynamic: requires-python
